Metadata-Version: 1.0
Name: udemyproj
Version: 1.0
Summary: Calculate and visuallize, Gaussian, Binomial and Normal distributions
Home-page: UNKNOWN
Author: UNKNOWN
Author-email: sjahnaviprasad@gmail.com
License: UNKNOWN
Platform: UNKNOWN
